hex_maze/__init__.py
hex_maze/board.py
hex_maze/tile.py
hex_maze-0.0.2.dist-info/LICENSE
hex_maze-0.0.2.dist-info/METADATA
hex_maze-0.0.2.dist-info/WHEEL
hex_maze-0.0.2.dist-info/top_level.txt
hex_maze-0.0.2.dist-info/RECORD
