Metadata-Version: 2.1
Name: hex-maze
Version: 0.0.2
Summary: Create random hexagonal mazes
Home-page: https://github.com/lebalz/hex-maze
Author: Balthasar Hofer
Author-email: lebalz@outlook.com
License: UNKNOWN
Platform: UNKNOWN
Classifier: Programming Language :: Python :: 3
Classifier: License :: OSI Approved :: MIT License
Classifier: Operating System :: OS Independent
Requires-Python: >=3.8
